__init__.py
fua.py
fua-1.0.2.dist-info/DESCRIPTION.rst
fua-1.0.2.dist-info/METADATA
fua-1.0.2.dist-info/RECORD
fua-1.0.2.dist-info/WHEEL
fua-1.0.2.dist-info/metadata.json
fua-1.0.2.dist-info/top_level.txt
