Metadata-Version: 2.0
Name: fua
Version: 1.0.2
Summary: Fake User-Agents of many real devices
Home-page: https://github.com/behdadahmadi
Author: Behdad Ahmadi
Author-email: behdadahmadi@mail.com
License: MIT
Keywords: sample setuptools development user-agent django flask user-agent fake http httplib urllib requests
Platform: UNKNOWN
Classifier: Development Status :: 5 - Production/Stable
Classifier: Intended Audience :: Developers
Classifier: Topic :: Software Development :: Build Tools
Classifier: License :: OSI Approved :: MIT License
Classifier: Programming Language :: Python :: 2.7
